LICENSE.md
roo/__init__.py
roo/caches/__init__.py
roo/caches/build_cache.py
roo/caches/source_cache.py
roo/caches/vcs_store.py
roo/cli/__init__.py
roo/cli/__main__.py
roo/cli/add/__init__.py
roo/cli/cache/__init__.py
roo/cli/ci/__init__.py
roo/cli/environment/__init__.py
roo/cli/export/__init__.py
roo/cli/init/__init__.py
roo/cli/install/__init__.py
roo/cli/lock/__init__.py
roo/cli/package/__init__.py
roo/cli/rswitch/__init__.py
roo/cli/run/__init__.py
roo/cli/x
roo/console.py
roo/deptree/__init__.py
roo/deptree/dependencies.py
roo/deptree/transforms.py
roo/deptree/traverse.py
roo/environment.py
roo/exporters/__init__.py
roo/exporters/exceptions.py
roo/exporters/lock/__init__.py
roo/exporters/lock/base_exporter.py
roo/exporters/lock/lock_csv_exporter.py
roo/exporters/lock/lock_packrat_exporter.py
roo/exporters/lock/lock_renv_exporter.py
roo/files/__init__.py
roo/files/rprofile.py
roo/hashing.py
roo/installer.py
roo/locker.py
roo/network.py
roo/parsers/__init__.py
roo/parsers/description.py
roo/parsers/exceptions.py
roo/parsers/lock.py
roo/parsers/rproject.py
roo/parsing_utils.py
roo/r_executor.py
roo/resolver.py
roo/semver/README.md
roo/semver/__init__.py
roo/semver/empty_constraint.py
roo/semver/exceptions.py
roo/semver/patterns.py
roo/semver/version.py
roo/semver/version_constraint.py
roo/semver/version_range.py
roo/semver/version_union.py
roo/sources/__init__.py
roo/sources/dir_package.py
roo/sources/exceptions.py
roo/sources/local_source.py
roo/sources/package_abc.py
roo/sources/remote_source.py
roo/sources/source_abc.py
roo/sources/source_group.py
roo/sources/source_package.py
roo/sources/vcs.py
roo-0.18.0.dist-info/LICENSE.md
roo-0.18.0.dist-info/METADATA
roo-0.18.0.dist-info/WHEEL
roo-0.18.0.dist-info/entry_points.txt
roo-0.18.0.dist-info/RECORD
