Metadata-Version: 2.1
Name: roo
Version: 0.18.0
Summary: A package manager to handle R environments
Home-page: https://github.com/AstraZeneca/roo
License: Apache-2.0
Keywords: R,packaging,environment,validation
Author: Stefano Borini
Author-email: stefano.borini@astrazeneca.com
Requires-Python: >=3.8,<4.0
Classifier: Development Status :: 4 - Beta
Classifier: Environment :: Console
Classifier: Intended Audience :: Developers
Classifier: License :: OSI Approved :: Apache Software License
Classifier: Programming Language :: Python
Classifier: Programming Language :: Python :: 3
Classifier: Programming Language :: Python :: 3.8
Classifier: Programming Language :: Python :: 3.9
Classifier: Programming Language :: Python :: 3.10
Classifier: Programming Language :: Python :: 3.11
Classifier: Programming Language :: Python :: 3.12
Classifier: Programming Language :: R
Classifier: Topic :: Software Development :: Build Tools
Requires-Dist: GitPython (>=3.1.13,<4.0.0)
Requires-Dist: atomicwrites (>=1.4,<2.0)
Requires-Dist: beautifulsoup4 (>=4.8.2,<5.0.0)
Requires-Dist: click (>=7.0,<8.0)
Requires-Dist: packaging (>=20.1,<21.0)
Requires-Dist: requests (>=2.22.0,<3.0.0)
Requires-Dist: rich (>=11.0.0,<12.0.0)
Requires-Dist: toml (>=0.10.0,<0.11.0)
Project-URL: Repository, https://github.com/AstraZeneca/roo
